[1,["45pLmWRnxBC6vPb0UI/w3S@6c48a"],["_textureSource"],["cc.SpriteFrame"],0,[{"name":"baoxiang3","rect":{"x":2,"y":2,"width":2022,"height":1134},"offset":{"x":-11,"y":455},"originalSize":{"width":2048,"height":2048},"rotated":false,"capInsets":[0,0,0,0],"vertices":{"rawPosition":[-1011,-567,0,1011,-567,0,-1011,567,0,1011,567,0],"indexes":[0,1,2,2,1,3],"uv":[2,2046,2024,2046,2,912,2024,912],"nuv":[0.0009765625,0.4453125,0.98828125,0.4453125,0.0009765625,0.9990234375,0.98828125,0.9990234375],"minPos":{"x":-1011,"y":-567,"z":0},"maxPos":{"x":1011,"y":567,"z":0}},"packable":true,"pixelsToUnit":100,"pivot":{"x":0.5,"y":0.5},"meshType":0}],[0],0,[0],[0],[0]]
